cdk_fargate_fastautoscaler/__init__.py
cdk_fargate_fastautoscaler/py.typed
cdk_fargate_fastautoscaler/_jsii/__init__.py
cdk_fargate_fastautoscaler/_jsii/cdk-fargate-fastautoscaler@0.2.97.jsii.tgz
cdk_fargate_fastautoscaler-0.2.97.dist-info/LICENSE
cdk_fargate_fastautoscaler-0.2.97.dist-info/METADATA
cdk_fargate_fastautoscaler-0.2.97.dist-info/WHEEL
cdk_fargate_fastautoscaler-0.2.97.dist-info/top_level.txt
cdk_fargate_fastautoscaler-0.2.97.dist-info/RECORD
